{"1.jpg": "Cả", "2.jpg": "sới", "3.jpg": "gà", "4.jpg": "náo", "5.jpg": "động", "6.jpg": "Lượng", "7.jpg": "tiền", "8.jpg": "cốp", "9.jpg": "tăng", "10.jpg": "chóng", "11.jpg": "mặt", "12.jpg": "tỉ", "13.jpg": "lệ", "14.jpg": "cá", "15.jpg": "cược", "16.jpg": "thay", "17.jpg": "đổi", "18.jpg": "liên", "19.jpg": "tục", "20.jpg": "Chỉ", "21.jpg": "trong", "22.jpg": "ít", "23.jpg": "phút", "24.jpg": "lượng", "25.jpg": "tiền", "26.jpg": "cược", "27.jpg": "trên", "28.jpg": "sàn", "29.jpg": "đã", "30.jpg": "lên", "31.jpg": "tới", "32.jpg": "vài", "33.jpg": "chục", "34.jpg": "triệu", "35.jpg": "đồng", "36.jpg": "Đã", "37.jpg": "hết", "38.jpg": "hồ", "39.jpg": "thứ", "40.jpg": "sáu", "41.jpg": "mỗi", "42.jpg": "trận", "43.jpg": "được", "44.jpg": "tính", "45.jpg": "làm", "46.jpg": "10", "47.jpg": "hồ", "48.jpg": "hiệp", "49.jpg": "đấu", "50.jpg": "mỗi", "51.jpg": "hồ", "52.jpg": "15", "53.jpg": "phút", "54.jpg": "cặp", "55.jpg": "gà", "56.jpg": "vẫn", "57.jpg": "chưa", "58.jpg": "phân", "59.jpg": "thắng", "60.jpg": "bại", "61.jpg": "Sới", "62.jpg": "tạm", "63.jpg": "nghỉ", "64.jpg": "cho", "65.jpg": "hai", "66.jpg": "đấu", "67.jpg": "thủ", "68.jpg": "hồi", "69.jpg": "sức", "70.jpg": "dân", "71.jpg": "đá", "72.jpg": "gà", "73.jpg": "tản", "74.jpg": "ra", "75.jpg": "ngồi", "76.jpg": "uống", "77.jpg": "nước", "78.jpg": "Tuấn", "79.jpg": "cụt", "80.jpg": "tỏ", "81.jpg": "ra", "82.jpg": "rất", "83.jpg": "vui", "84.jpg": "vì", "85.jpg": "đã", "86.jpg": "dốc", "87.jpg": "gần", "88.jpg": "5", "89.jpg": "triệu", "90.jpg": "cho", "91.jpg": "trận", "92.jpg": "đá", "93.jpg": "này", "94.jpg": "Chân", "95.jpg": "dung", "96.jpg": "những", "97.jpg": "kẻ", "98.jpg": "bạc", "99.jpg": "gà", "100.jpg": "Có", "101.jpg": "lẽ", "102.jpg": "cuộc", "103.jpg": "đời", "104.jpg": "của", "105.jpg": "Tuấn", "106.jpg": "cụt", "107.jpg": "đã", "108.jpg": "là", "109.jpg": "một", "110.jpg": "minh", "111.jpg": "chứng", "112.jpg": "tiêu", "113.jpg": "biểu", "114.jpg": "cho", "115.jpg": "triết", "116.jpg": "lý", "117.jpg": "chơi", "118.jpg": "gà", "119.jpg": "chọi", "120.jpg": "là", "121.jpg": "cái", "122.jpg": "nợ", "123.jpg": "đời", "124.jpg": "Hắn", "125.jpg": "biết", "126.jpg": "chơi", "127.jpg": "gà", "128.jpg": "và", "129.jpg": "ham", "130.jpg": "gà", "131.jpg": "chọi", "132.jpg": "từ", "133.jpg": "ngày", "134.jpg": "còn", "135.jpg": "thò", "136.jpg": "lò", "137.jpg": "mũi", "138.jpg": "xanh", "139.jpg": "đến", "140.jpg": "nay", "141.jpg": "hắn", "142.jpg": "đã", "143.jpg": "41", "144.jpg": "tuổi", "145.jpg": "Gần", "146.jpg": "30", "147.jpg": "năm", "148.jpg": "lăn", "149.jpg": "lộn", "150.jpg": "trong", "151.jpg": "nghề", "152.jpg": "đã", "153.jpg": "khiến", "154.jpg": "hắn", "155.jpg": "trở", "156.jpg": "thành", "157.jpg": "một", "158.jpg": "tay", "159.jpg": "bạc", "160.jpg": "gà", "161.jpg": "lão", "162.jpg": "luyện", "163.jpg": "của", "164.jpg": "vùng", "165.jpg": "Bắc", "166.jpg": "bộ", "167.jpg": "Chưa", "168.jpg": "trận", "169.jpg": "nào", "170.jpg": "hắn", "171.jpg": "chơi", "172.jpg": "dưới", "173.jpg": "2", "174.jpg": "triệu", "175.jpg": "trận", "176.jpg": "nào", "177.jpg": "kết", "178.jpg": "hắn", "179.jpg": "chơi", "180.jpg": "hơn", "181.jpg": "chục", "182.jpg": "triệu", "183.jpg": "là", "184.jpg": "chuyện", "185.jpg": "thường", "186.jpg": "Hắn", "187.jpg": "đã", "188.jpg": "lập", "189.jpg": "gia", "190.jpg": "đình", "191.jpg": "nhưng", "192.jpg": "cái", "193.jpg": "gia", "194.jpg": "đình", "195.jpg": "ấy", "196.jpg": "đã", "197.jpg": "tan", "198.jpg": "vỡ", "199.jpg": "Thế", "200.jpg": "nhưng", "201.jpg": "mức", "202.jpg": "độ", "203.jpg": "chơi", "204.jpg": "bạc", "205.jpg": "gà", "206.jpg": "của", "207.jpg": "Tuấn", "208.jpg": "cụt", "209.jpg": "chưa", "210.jpg": "ăn", "211.jpg": "thua", "212.jpg": "gì", "213.jpg": "so", "214.jpg": "với", "215.jpg": "Hậu", "216.jpg": "trọc", "217.jpg": "Dân", "218.jpg": "đá", "219.jpg": "gà", "220.jpg": "miền", "221.jpg": "Bắc", "222.jpg": "chỉ", "223.jpg": "biết", "224.jpg": "hắn", "225.jpg": "có", "226.jpg": "hộ", "227.jpg": "khẩu", "228.jpg": "thường", "229.jpg": "trú", "230.jpg": "tại", "231.jpg": "Hà", "232.jpg": "Nội", "233.jpg": "chứ", "234.jpg": "không", "235.jpg": "ai", "236.jpg": "biết", "237.jpg": "chính", "238.jpg": "xác", "239.jpg": "hắn", "240.jpg": "làm", "241.jpg": "nghề", "242.jpg": "gì", "243.jpg": "Hắn", "244.jpg": "thường", "245.jpg": "hay", "246.jpg": "bê", "247.jpg": "gà", "248.jpg": "đi", "249.jpg": "khắp", "250.jpg": "các", "251.jpg": "sới", "252.jpg": "bằng", "253.jpg": "chiếc", "254.jpg": "ôtô", "255.jpg": "hiệu", "256.jpg": "Camry", "257.jpg": "trị", "258.jpg": "giá", "259.jpg": "vài", "260.jpg": "chục", "261.jpg": "ngàn", "262.jpg": "USD", "263.jpg": "của", "264.jpg": "mình", "265.jpg": "Hắn", "266.jpg": "đã", "267.jpg": "từng", "268.jpg": "chơi", "269.jpg": "những", "270.jpg": "trận", "271.jpg": "cá", "272.jpg": "cược", "273.jpg": "gà", "274.jpg": "hơn", "275.jpg": "50", "276.jpg": "triệu", "277.jpg": "đồng", "278.jpg": "Nói", "279.jpg": "đến", "280.jpg": "chân", "281.jpg": "dung", "282.jpg": "những", "283.jpg": "kẻ", "284.jpg": "bạc", "285.jpg": "gà", "286.jpg": "không", "287.jpg": "thể", "288.jpg": "quên", "289.jpg": "những", "290.jpg": "tay", "291.jpg": "chủ", "292.jpg": "sới", "293.jpg": "Phần", "294.jpg": "nhiều", "295.jpg": "họ", "296.jpg": "là", "297.jpg": "những", "298.jpg": "thành", "299.jpg": "phần", "300.jpg": "có", "301.jpg": "máu", "302.jpg": "mặt", "303.jpg": "ở", "304.jpg": "địa", "305.jpg": "phương", "306.jpg": "nếu", "307.jpg": "chỉ", "308.jpg": "là", "309.jpg": "người", "310.jpg": "bình", "311.jpg": "thường", "312.jpg": "chắc", "313.jpg": "chẳng", "314.jpg": "đủ", "315.jpg": "gan", "316.jpg": "để", "317.jpg": "mở", "318.jpg": "một", "319.jpg": "sới", "320.jpg": "ngay", "321.jpg": "giữa", "322.jpg": "ban", "323.jpg": "ngày", "324.jpg": "ban", "325.jpg": "mặt", "326.jpg": "Họ", "327.jpg": "đồng", "328.jpg": "thời", "329.jpg": "cũng", "330.jpg": "là", "331.jpg": "những", "332.jpg": "tín", "333.jpg": "đồ", "334.jpg": "của", "335.jpg": "đạo", "336.jpg": "bạc", "337.jpg": "gà", "338.jpg": "Họ", "339.jpg": "mở", "340.jpg": "sới", "341.jpg": "không", "342.jpg": "phải", "343.jpg": "chỉ", "344.jpg": "là", "345.jpg": "tạo", "346.jpg": "sân", "347.jpg": "chơi", "348.jpg": "lành", "349.jpg": "mạnh", "350.jpg": "cho", "351.jpg": "dân", "352.jpg": "mê", "353.jpg": "gà", "354.jpg": "mà", "355.jpg": "cốt", "356.jpg": "để", "357.jpg": "kinh", "358.jpg": "doanh", "359.jpg": "thu", "360.jpg": "tiền", "361.jpg": "sới", "362.jpg": "sau", "363.jpg": "mỗi", "364.jpg": "trận", "365.jpg": "đấu", "366.jpg": "trong", "367.jpg": "đó", "368.jpg": "bao", "369.jpg": "gồm", "370.jpg": "cả", "371.jpg": "phí", "372.jpg": "an", "373.jpg": "ninh", "374.jpg": "phí", "375.jpg": "liên", "376.jpg": "lạc", "377.jpg": "Đó", "378.jpg": "là", "379.jpg": "chưa", "380.jpg": "kể", "381.jpg": "hàng", "382.jpg": "trăm", "383.jpg": "thứ", "384.jpg": "dịch", "385.jpg": "vụ", "386.jpg": "kèm", "387.jpg": "theo", "388.jpg": "như", "389.jpg": "ăn", "390.jpg": "uống", "391.jpg": "giữ", "392.jpg": "xe", "393.jpg": "với", "394.jpg": "mức", "395.jpg": "giá", "396.jpg": "cắt", "397.jpg": "cổ", "398.jpg": "Tính", "399.jpg": "nhẩm", "400.jpg": "ra", "401.jpg": "nếu", "402.jpg": "ngày", "403.jpg": "nào", "404.jpg": "đông", "405.jpg": "khách", "406.jpg": "mỗi", "407.jpg": "phường", "408.jpg": "gà", "409.jpg": "thu", "410.jpg": "nhập", "411.jpg": "không", "412.jpg": "dưới", "413.jpg": "tiền", "414.jpg": "triệu"}